{
    "os": "Linux-5.4.56.bsk.10-amd64-x86_64-with-glibc2.31",
    "python": "3.9.2",
    "heartbeatAt": "2023-07-17T08:55:55.859690",
    "startedAt": "2023-07-17T08:55:48.309512",
    "docker": null,
    "cuda": null,
    "args": [
        "--config",
        "./configs/instruction_tuning_bloom_560m.yaml"
    ],
    "state": "running",
    "program": "/mnt/bn/multimodal-moderation-xh/Code/AudioLLM-AST/st_instruc_tuning.py",
    "codePath": "st_instruc_tuning.py",
    "host": "n213-020-036",
    "username": "tiger",
    "executable": "/usr/bin/python3",
    "cpu_count": 64,
    "cpu_count_logical": 128,
    "cpu_freq": {
        "current": 2994.9557343750002,
        "min": 800.0,
        "max": 3500.0
    },
    "cpu_freq_per_core": [
        {
            "current": 3000.0,
            "min": 800.0,
            "max": 3500.0
        },
        {
            "current": 3012.048,
            "min": 800.0,
            "max": 3500.0
        },
        {
            "current": 3011.904,
            "min": 800.0,
            "max": 3500.0
        },
        {
            "current": 2999.131,
            "min": 800.0,
            "max": 3500.0
        },
        {
            "current": 3000.124,
            "min": 800.0,
            "max": 3500.0
        },
        {
            "current": 2999.703,
            "min": 800.0,
            "max": 3500.0
        },
        {
            "current": 3000.0,
            "min": 800.0,
            "max": 3500.0
        },
        {
            "current": 3000.904,
            "min": 800.0,
            "max": 3500.0
        },
        {
            "current": 3000.0,
            "min": 800.0,
            "max": 3500.0
        },
        {
            "current": 3000.0,
            "min": 800.0,
            "max": 3500.0
        },
        {
            "current": 3012.244,
            "min": 800.0,
            "max": 3500.0
        },
        {
            "current": 3001.255,
            "min": 800.0,
            "max": 3500.0
        },
        {
            "current": 3012.5,
            "min": 800.0,
            "max": 3500.0
        },
        {
            "current": 2992.021,
            "min": 800.0,
            "max": 3500.0
        },
        {
            "current": 3000.0,
            "min": 800.0,
            "max": 3500.0
        },
        {
            "current": 2999.24,
            "min": 800.0,
            "max": 3500.0
        },
        {
            "current": 3000.0,
            "min": 800.0,
            "max": 3500.0
        },
        {
            "current": 3000.0,
            "min": 800.0,
            "max": 3500.0
        },
        {
            "current": 3011.904,
            "min": 800.0,
            "max": 3500.0
        },
        {
            "current": 3000.0,
            "min": 800.0,
            "max": 3500.0
        },
        {
            "current": 3000.0,
            "min": 800.0,
            "max": 3500.0
        },
        {
            "current": 3012.295,
            "min": 800.0,
            "max": 3500.0
        },
        {
            "current": 2998.229,
            "min": 800.0,
            "max": 3500.0
        },
        {
            "current": 2953.538,
            "min": 800.0,
            "max": 3500.0
        },
        {
            "current": 3000.0,
            "min": 800.0,
            "max": 3500.0
        },
        {
            "current": 3000.0,
            "min": 800.0,
            "max": 3500.0
        },
        {
            "current": 3000.0,
            "min": 800.0,
            "max": 3500.0
        },
        {
            "current": 2988.764,
            "min": 800.0,
            "max": 3500.0
        },
        {
            "current": 3010.714,
            "min": 800.0,
            "max": 3500.0
        },
        {
            "current": 2950.798,
            "min": 800.0,
            "max": 3500.0
        },
        {
            "current": 2997.995,
            "min": 800.0,
            "max": 3500.0
        },
        {
            "current": 3000.0,
            "min": 800.0,
            "max": 3500.0
        },
        {
            "current": 2943.412,
            "min": 800.0,
            "max": 3500.0
        },
        {
            "current": 3000.0,
            "min": 800.0,
            "max": 3500.0
        },
        {
            "current": 3000.0,
            "min": 800.0,
            "max": 3500.0
        },
        {
            "current": 3000.0,
            "min": 800.0,
            "max": 3500.0
        },
        {
            "current": 3013.157,
            "min": 800.0,
            "max": 3500.0
        },
        {
            "current": 3000.0,
            "min": 800.0,
            "max": 3500.0
        },
        {
            "current": 3000.0,
            "min": 800.0,
            "max": 3500.0
        },
        {
            "current": 3013.953,
            "min": 800.0,
            "max": 3500.0
        },
        {
            "current": 2999.302,
            "min": 800.0,
            "max": 3500.0
        },
        {
            "current": 3000.0,
            "min": 800.0,
            "max": 3500.0
        },
        {
            "current": 2998.896,
            "min": 800.0,
            "max": 3500.0
        },
        {
            "current": 3000.0,
            "min": 800.0,
            "max": 3500.0
        },
        {
            "current": 2951.508,
            "min": 800.0,
            "max": 3500.0
        },
        {
            "current": 3000.0,
            "min": 800.0,
            "max": 3500.0
        },
        {
            "current": 2998.858,
            "min": 800.0,
            "max": 3500.0
        },
        {
            "current": 3001.714,
            "min": 800.0,
            "max": 3500.0
        },
        {
            "current": 3000.0,
            "min": 800.0,
            "max": 3500.0
        },
        {
            "current": 3000.0,
            "min": 800.0,
            "max": 3500.0
        },
        {
            "current": 3000.0,
            "min": 800.0,
            "max": 3500.0
        },
        {
            "current": 2999.006,
            "min": 800.0,
            "max": 3500.0
        },
        {
            "current": 2997.802,
            "min": 800.0,
            "max": 3500.0
        },
        {
            "current": 3000.127,
            "min": 800.0,
            "max": 3500.0
        },
        {
            "current": 3000.0,
            "min": 800.0,
            "max": 3500.0
        },
        {
            "current": 2998.623,
            "min": 800.0,
            "max": 3500.0
        },
        {
            "current": 3000.0,
            "min": 800.0,
            "max": 3500.0
        },
        {
            "current": 3000.928,
            "min": 800.0,
            "max": 3500.0
        },
        {
            "current": 3000.0,
            "min": 800.0,
            "max": 3500.0
        },
        {
            "current": 3000.0,
            "min": 800.0,
            "max": 3500.0
        },
        {
            "current": 2951.309,
            "min": 800.0,
            "max": 3500.0
        },
        {
            "current": 3000.003,
            "min": 800.0,
            "max": 3500.0
        },
        {
            "current": 3000.232,
            "min": 800.0,
            "max": 3500.0
        },
        {
            "current": 3000.3,
            "min": 800.0,
            "max": 3500.0
        },
        {
            "current": 3000.0,
            "min": 800.0,
            "max": 3500.0
        },
        {
            "current": 3000.0,
            "min": 800.0,
            "max": 3500.0
        },
        {
            "current": 3000.374,
            "min": 800.0,
            "max": 3500.0
        },
        {
            "current": 3000.0,
            "min": 800.0,
            "max": 3500.0
        },
        {
            "current": 3000.0,
            "min": 800.0,
            "max": 3500.0
        },
        {
            "current": 3000.0,
            "min": 800.0,
            "max": 3500.0
        },
        {
            "current": 3000.0,
            "min": 800.0,
            "max": 3500.0
        },
        {
            "current": 3000.0,
            "min": 800.0,
            "max": 3500.0
        },
        {
            "current": 2998.076,
            "min": 800.0,
            "max": 3500.0
        },
        {
            "current": 3000.0,
            "min": 800.0,
            "max": 3500.0
        },
        {
            "current": 3001.98,
            "min": 800.0,
            "max": 3500.0
        },
        {
            "current": 3000.0,
            "min": 800.0,
            "max": 3500.0
        },
        {
            "current": 3012.0,
            "min": 800.0,
            "max": 3500.0
        },
        {
            "current": 2950.117,
            "min": 800.0,
            "max": 3500.0
        },
        {
            "current": 3000.0,
            "min": 800.0,
            "max": 3500.0
        },
        {
            "current": 2999.992,
            "min": 800.0,
            "max": 3500.0
        },
        {
            "current": 3011.45,
            "min": 800.0,
            "max": 3500.0
        },
        {
            "current": 3003.973,
            "min": 800.0,
            "max": 3500.0
        },
        {
            "current": 3012.145,
            "min": 800.0,
            "max": 3500.0
        },
        {
            "current": 3000.0,
            "min": 800.0,
            "max": 3500.0
        },
        {
            "current": 2988.095,
            "min": 800.0,
            "max": 3500.0
        },
        {
            "current": 3000.0,
            "min": 800.0,
            "max": 3500.0
        },
        {
            "current": 3000.0,
            "min": 800.0,
            "max": 3500.0
        },
        {
            "current": 2980.941,
            "min": 800.0,
            "max": 3500.0
        },
        {
            "current": 3000.0,
            "min": 800.0,
            "max": 3500.0
        },
        {
            "current": 2999.7,
            "min": 800.0,
            "max": 3500.0
        },
        {
            "current": 3000.0,
            "min": 800.0,
            "max": 3500.0
        },
        {
            "current": 2988.764,
            "min": 800.0,
            "max": 3500.0
        },
        {
            "current": 3000.0,
            "min": 800.0,
            "max": 3500.0
        },
        {
            "current": 2800.0,
            "min": 800.0,
            "max": 3500.0
        },
        {
            "current": 3000.0,
            "min": 800.0,
            "max": 3500.0
        },
        {
            "current": 3000.0,
            "min": 800.0,
            "max": 3500.0
        },
        {
            "current": 2961.573,
            "min": 800.0,
            "max": 3500.0
        },
        {
            "current": 3000.0,
            "min": 800.0,
            "max": 3500.0
        },
        {
            "current": 2997.943,
            "min": 800.0,
            "max": 3500.0
        },
        {
            "current": 3000.232,
            "min": 800.0,
            "max": 3500.0
        },
        {
            "current": 2999.846,
            "min": 800.0,
            "max": 3500.0
        },
        {
            "current": 3000.372,
            "min": 800.0,
            "max": 3500.0
        },
        {
            "current": 3001.14,
            "min": 800.0,
            "max": 3500.0
        },
        {
            "current": 3002.624,
            "min": 800.0,
            "max": 3500.0
        },
        {
            "current": 2999.011,
            "min": 800.0,
            "max": 3500.0
        },
        {
            "current": 2999.745,
            "min": 800.0,
            "max": 3500.0
        },
        {
            "current": 3000.0,
            "min": 800.0,
            "max": 3500.0
        },
        {
            "current": 3000.0,
            "min": 800.0,
            "max": 3500.0
        },
        {
            "current": 2938.78,
            "min": 800.0,
            "max": 3500.0
        },
        {
            "current": 3000.0,
            "min": 800.0,
            "max": 3500.0
        },
        {
            "current": 3000.0,
            "min": 800.0,
            "max": 3500.0
        },
        {
            "current": 3000.0,
            "min": 800.0,
            "max": 3500.0
        },
        {
            "current": 3000.0,
            "min": 800.0,
            "max": 3500.0
        },
        {
            "current": 3000.0,
            "min": 800.0,
            "max": 3500.0
        },
        {
            "current": 3002.173,
            "min": 800.0,
            "max": 3500.0
        },
        {
            "current": 3000.0,
            "min": 800.0,
            "max": 3500.0
        },
        {
            "current": 3000.0,
            "min": 800.0,
            "max": 3500.0
        },
        {
            "current": 3000.0,
            "min": 800.0,
            "max": 3500.0
        },
        {
            "current": 3000.0,
            "min": 800.0,
            "max": 3500.0
        },
        {
            "current": 3000.0,
            "min": 800.0,
            "max": 3500.0
        },
        {
            "current": 3000.0,
            "min": 800.0,
            "max": 3500.0
        },
        {
            "current": 3000.0,
            "min": 800.0,
            "max": 3500.0
        },
        {
            "current": 3000.0,
            "min": 800.0,
            "max": 3500.0
        },
        {
            "current": 3000.012,
            "min": 800.0,
            "max": 3500.0
        },
        {
            "current": 2963.681,
            "min": 800.0,
            "max": 3500.0
        },
        {
            "current": 3001.662,
            "min": 800.0,
            "max": 3500.0
        },
        {
            "current": 3000.0,
            "min": 800.0,
            "max": 3500.0
        },
        {
            "current": 3000.0,
            "min": 800.0,
            "max": 3500.0
        }
    ],
    "disk": {
        "total": 1648.927318572998,
        "used": 588.6852111816406
    },
    "gpu": "A100-SXM-80GB",
    "gpu_count": 1,
    "gpu_devices": [
        {
            "name": "A100-SXM-80GB",
            "memory_total": 85199093760
        }
    ],
    "memory": {
        "total": 2015.234992980957
    }
}
